streamparser.py
apertium_streamparser-5.0.2.dist-info/METADATA
apertium_streamparser-5.0.2.dist-info/RECORD
apertium_streamparser-5.0.2.dist-info/WHEEL
apertium_streamparser-5.0.2.dist-info/entry_points.txt
apertium_streamparser-5.0.2.dist-info/top_level.txt
