Metadata-Version: 2.1
Name: apertium-streamparser
Version: 5.0.2
Summary: Python library to parse Apertium stream format
Home-page: https://github.com/apertium/streamparser
Author: Sushain K. Cherivirala
Author-email: sushain@skc.name
License: GPLv3+
Keywords: apertium parsing linguistics
Platform: UNKNOWN
Classifier: Development Status :: 5 - Production/Stable
Classifier: Topic :: Text Processing :: Linguistic
Classifier: License :: OSI Approved :: GNU General Public License v3 or later (GPLv3+)
Classifier: Intended Audience :: Science/Research
Classifier: Intended Audience :: Developers
Classifier: Programming Language :: Python :: 3.4
Classifier: Programming Language :: Python :: 3.5
Classifier: Programming Language :: Python :: 3.6
Classifier: Programming Language :: Python :: 3 :: Only
Classifier: Programming Language :: Python :: Implementation :: PyPy
Classifier: Programming Language :: Python :: Implementation :: CPython
Requires-Python: >=3.4
